{
  "type": "table",
  "block_id": "table_block_1",
  "column_settings": [
    {
      "is_wrapped": true
    },
    {
      "align": "right"
    }
  ],
  "rows": [
    [
      {
        "type": "raw_text",
        "text": "Header A"
      },
      {
        "type": "raw_text",
        "text": "Header B"
      }
    ],
    [
      {
        "type": "raw_text",
        "text": "Data 1A"
      },
      {
        "type": "rich_text",
        "elements": [
          {
            "type": "rich_text_section",
            "elements": [
              {
                "type": "link",
                "url": "https://slack.com",
                "text": "Data 1B"
              }
            ]
          }
        ]
      }
    ]
  ]
}
